ragflow_client/__init__.py
ragflow_client/cli.py
ragflow_client/client.py
ragflow_client/api/__init__.py
ragflow_client/api/chat.py
ragflow_client/api/chat_assistant.py
ragflow_client/api/chat_session.py
ragflow_client/api/dataset.py
ragflow_client/api/document.py
ragflow_client/api/prompt/__init__.py
ragflow_client/api/prompt/chat_prompt.py
ragflow_client/config/__init__.py
ragflow_client/config/config.py
ragflow_client/utils/__init__.py
ragflow_client/utils/api_utils.py
ragflow_client-0.1.1.dist-info/licenses/LICENSE.md
ragflow_client-0.1.1.dist-info/METADATA
ragflow_client-0.1.1.dist-info/WHEEL
ragflow_client-0.1.1.dist-info/entry_points.txt
ragflow_client-0.1.1.dist-info/top_level.txt
ragflow_client-0.1.1.dist-info/RECORD
