Metadata-Version: 2.4
Name: ragflow-client
Version: 0.1.1
Summary: Python client for RagFlow API
Home-page: https://github.com/blackdwarftech/ragflow-client
Author: BLACKDWARF
Author-email: blackdwarftech@gmail.com
Classifier: Programming Language :: Python :: 3
Classifier: License :: OSI Approved :: MIT License
Classifier: Operating System :: OS Independent
Requires-Python: >=3.8
License-File: LICENSE.md
Requires-Dist: requests>=2.25.0
Requires-Dist: python-dotenv>=0.15.0
Requires-Dist: ragflow-sdk>=0.15.0
Requires-Dist: tqdm>=4.61.0
Dynamic: author
Dynamic: author-email
Dynamic: classifier
Dynamic: description
Dynamic: description-content-type
Dynamic: home-page
Dynamic: license-file
Dynamic: requires-dist
Dynamic: requires-python
Dynamic: summary
